{"Companies":[{"CompanyName":"GOOG","Actions":[{"date":"2022-01-11","Commission":"30.0","Quantity":"0.29","action":"buy"},{"date":"2022-02-10","Commission":"30.0","Quantity":"0.29","action":"buy"},{"date":"2022-03-14","Commission":"30.0","Quantity":"0.32","action":"buy"},{"date":"2022-04-11","Commission":"30.0","Quantity":"0.31","action":"buy"},{"date":"2022-05-11","Commission":"30.0","Quantity":"0.35","action":"buy"},{"date":"2022-06-10","Commission":"30.0","Quantity":"0.36","action":"buy"},{"date":"2022-07-11","Commission":"30.0","Quantity":"0.34","action":"buy"},{"date":"2022-08-09","Commission":"30.0","Quantity":"6.81","action":"buy"},{"date":"2022-09-08","Commission":"30.0","Quantity":"7.31","action":"buy"},{"date":"2022-10-10","Commission":"30.0","Quantity":"8.10","action":"buy"},{"date":"2022-11-07","Commission":"30.0","Quantity":"9.02","action":"buy"}]},{"CompanyName":"META","Actions":[{"date":"2022-01-11","Commission":"30.0","Quantity":"3.59","action":"buy"},{"date":"2022-02-10","Commission":"30.0","Quantity":"5.26","action":"buy"},{"date":"2022-03-14","Commission":"30.0","Quantity":"6.43","action":"buy"},{"date":"2022-04-11","Commission":"30.0","Quantity":"5.54","action":"buy"},{"date":"2022-05-11","Commission":"30.0","Quantity":"6.36","action":"buy"},{"date":"2022-06-10","Commission":"30.0","Quantity":"6.83","action":"buy"},{"date":"2022-07-11","Commission":"30.0","Quantity":"7.37","action":"buy"},{"date":"2022-08-09","Commission":"30.0","Quantity":"7.12","action":"buy"},{"date":"2022-09-08","Commission":"30.0","Quantity":"7.40","action":"buy"},{"date":"2022-10-10","Commission":"30.0","Quantity":"8.97","action":"buy"},{"date":"2022-11-07","Quantity":"12.41","action":"buy","Commission":"30.0"}]}],"type":"flexible"}