{
  "Companies": [
    {
      "CompanyName": "goog",
      "Actions": [
        {
          "date": "2021-02-12",
          "Quantity": "20.0",
          "action": "buy"
        },
        {
          "date": "2021-04-10",
          "Quantity": "10.0",
          "action": "buy"
        },
        {
          "date": "2021-03-10",
          "Quantity": "10.0",
          "action": "sell"
        },
        {
          "date": "2020-01-10",
          "Quantity": "5.0",
          "action": "buy"
        },
        {
          "date": "2021-03-14",
          "Quantity": "2.0",
          "action": "sell"
        },
        {
          "date": "2020-11-11",
          "Quantity": "10.0",
          "action": "buy"
        }
      ]
    },
    {
      "CompanyName": "amzn",
      "Actions": [
        {
          "date": "2022-10-01",
          "Quantity": "10.0",
          "action": "buy"
        },
        {
          "date": "2022-11-11",
          "Quantity": "5",
          "action": "sell"
        },
        {
          "date": "2022-11-11",
          "Quantity": "10",
          "action": "buy"
        }
      ]
    },
    {
      "CompanyName": "twtr",
      "Actions": [
        {
          "date": "2022-11-11",
          "Quantity": "10",
          "action": "buy"
        },
        {
          "date": "2022-11-11",
          "Quantity": "20",
          "action": "buy"
        },
        {
          "date": "2022-11-11",
          "Quantity": "20",
          "action": "buy"
        },
        {
          "date": "2009-09-09",
          "Quantity": "12",
          "action": "buy"
        },
        {
          "date": "2007-09-09",
          "Quantity": "3",
          "action": "buy"
        },
        {
          "date": "2022-11-13",
          "Quantity": "10",
          "action": "sell"
        }
      ]
    }
  ],
  "type": "flexible"
}